maplearn/__init__.py
maplearn/__main__.py
maplearn/logging.cfg
maplearn/run.py
maplearn/run_example.py
maplearn/run_gui.py
maplearn/app/__init__.py
maplearn/app/cli.py
maplearn/app/config.py
maplearn/app/main.py
maplearn/app/reporting.py
maplearn/app/static_dict.py
maplearn/app/doc/fr_index.html
maplearn/app/doc/fr_io.html
maplearn/app/doc/fr_preprocess.html
maplearn/app/doc/fr_process.html
maplearn/app/gui/__init__.py
maplearn/app/gui/gui.py
maplearn/app/gui/maplearn_rc.py
maplearn/app/gui/maplearn_ui.py
maplearn/app/gui/Icon/English-Flag-icon.png
maplearn/app/gui/Icon/English-Flag-icon2.png
maplearn/app/gui/Icon/France-Flag-icon.png
maplearn/app/gui/Icon/France-Flag-icon2.png
maplearn/app/gui/Icon/exit_icon.png
maplearn/app/gui/Icon/io_icon.png
maplearn/app/gui/Icon/logo.png
maplearn/app/gui/Icon/new-icon.png
maplearn/app/gui/Icon/open-icon.png
maplearn/app/gui/Icon/preprocess-icon.png
maplearn/app/gui/Icon/preprocess_icon.png
maplearn/app/gui/Icon/process_icon.png
maplearn/app/gui/Icon/quit-icon.png
maplearn/app/gui/Icon/save-icon.png
maplearn/app/gui/Icon/saveas-icon.png
maplearn/app/img/error.png
maplearn/app/img/info.png
maplearn/app/img/logo.png
maplearn/app/img/warning.png
maplearn/app/style/style.css
maplearn/datahandler/__init__.py
maplearn/datahandler/labels.py
maplearn/datahandler/loader.py
maplearn/datahandler/packdata.py
maplearn/datahandler/plotter.py
maplearn/datahandler/signature.py
maplearn/datahandler/writer.py
maplearn/datasets/README.md
maplearn/datasets/classif_landsat_rennes.qml
maplearn/datasets/data.dbf
maplearn/datasets/data.prj
maplearn/datasets/data.qpj
maplearn/datasets/data.shp
maplearn/datasets/data.shx
maplearn/datasets/echantillon.dbf
maplearn/datasets/echantillon.prj
maplearn/datasets/echantillon.sbn
maplearn/datasets/echantillon.sbx
maplearn/datasets/echantillon.shp
maplearn/datasets/echantillon.shx
maplearn/datasets/echantillon_rennes.csv
maplearn-0.3.8.dist-info/DESCRIPTION.rst
maplearn-0.3.8.dist-info/METADATA
maplearn-0.3.8.dist-info/RECORD
maplearn-0.3.8.dist-info/WHEEL
maplearn-0.3.8.dist-info/entry_points.txt
maplearn-0.3.8.dist-info/metadata.json
maplearn-0.3.8.dist-info/top_level.txt
