Metadata-Version: 2.0
Name: maplearn
Version: 0.3.8
Summary: Mapping Learning
Home-page: https://bitbucket.org/thomas_a/maplearn/
Author: Alban Thomas
Author-email: alban.thomas@univ-rennes2.fr
License: LGPL
Platform: any
Classifier: Development Status :: 3 - Alpha
Classifier: Environment :: Console
Classifier: Environment :: Win32 (MS Windows)
Classifier: Environment :: X11 Applications
Classifier: Framework :: Sphinx
Classifier: Intended Audience :: Education
Classifier: Intended Audience :: End Users/Desktop
Classifier: Intended Audience :: Science/Research
Classifier: License :: OSI Approved :: GNU Lesser General Public License v3 (LGPLv3)
Classifier: Natural Language :: French
Classifier: Programming Language :: Python
Classifier: Programming Language :: Python :: 2
Classifier: Programming Language :: Python :: 2.7
Classifier: Programming Language :: Python :: 3
Classifier: Programming Language :: Python :: 3.5
Classifier: Programming Language :: Python :: 3.6
Classifier: Programming Language :: Python :: 3.7
Classifier: Topic :: Education
Classifier: Topic :: Scientific/Engineering :: Artificial Intelligence
Classifier: Topic :: Scientific/Engineering :: Atmospheric Science
Requires-Dist: pandas
Requires-Dist: numpy
Requires-Dist: scipy
Requires-Dist: statsmodels (>=0.7)
Requires-Dist: patsy
Requires-Dist: scikit-learn (>=0.18.1)
Requires-Dist: markdown
Requires-Dist: matplotlib
Requires-Dist: GDAL
Requires-Dist: xlrd
Requires-Dist: xlwt
Requires-Dist: openpyxl
Requires-Dist: pytest
Requires-Dist: seaborn
